testeron/__init__.py
testeron/main.py
testeron/.system/imports.py
testeron/.system/index.py
testeron/.system/modules/jobs.py
testeron/.system/sources/clight.json
testeron/.system/sources/logo.ico
testeron-0.0.5.dist-info/LICENSE
testeron-0.0.5.dist-info/METADATA
testeron-0.0.5.dist-info/WHEEL
testeron-0.0.5.dist-info/entry_points.txt
testeron-0.0.5.dist-info/top_level.txt
testeron-0.0.5.dist-info/RECORD
